Workbook

Sheet employees
A1: employee_id | B1: name | C1: gender | D1: age | E1: department_id | F1: department_name | G1: department_category | H1: location_id | I1: City | J1: Continent | K1: seniority | L1: education | M1: hire_date | N1: work_mode | O1: performance_score | P1: satisfaction_score | Q1: initial_salary_usd | R1: manager_id | S1: Tenure | T1: cost_index | U1: Cost Adjusted Salary
A2: 1 | B2: Allison Hill | C2: Male | D2: 34 | E2: 21 | F2: =VLOOKUP(Table6[[#This Row],[department_id]],departments[#All],2,FALSE) -> Finance | G2: =VLOOKUP(employees!$E2,departments[],3,FALSE) -> G&A | H2: 4 | I2: =VLOOKUP(employees!$H2,locations[#All],3,FALSE) -> Toronto | J2: =_xlfn.XLOOKUP(Table6[[#This Row],[City]],locations[city],locations[Continent]) -> North America | K2: Intern | L2: Bachelor | M2: 43893 | N2: On-site | O2: 4.2 | P2: 7.6 | Q2: 39578.39 | R2: 2177 | S2: =DATEDIF(employees!$M2, TODAY(), "y") -> 6 | T2: =VLOOKUP(employees!$H2,locations[#All],4,) -> 1.1 | U2: =employees!$Q2/employees!$T2 -> 35980.355
A3: 2 | B3: Noah Rhodes | C3: Non-binary | D3: 32 | E3: 3 | F3: =VLOOKUP(Table6[[#This Row],[department_id]],departments[#All],2,FALSE) -> Data Engineering | G3: =VLOOKUP(employees!$E3,departments[],3,FALSE) -> Tech | H3: 7 | I3: =VLOOKUP(employees!$H3,locations[#All],3,FALSE) -> Paris | J3: =_xlfn.XLOOKUP(Table6[[#This Row],[City]],locations[city],locations[Continent]) -> Europe | K3: Mid | L3: Master | M3: 41857 | N3: Hybrid | O3: 3.46 | P3: 7.2 | Q3: 141489.28 | R3: 2225 | S3: =DATEDIF(employees!$M3, TODAY(), "y") -> 12 | T3: =VLOOKUP(employees!$H3,locations[#All],4,) -> 1.18 | U3: =employees!$Q3/employees!$T3 -> 119906.17
A4: 3 | B4: Angie Henderson | C4: Female | D4: 29 | E4: 25 | F4: =VLOOKUP(Table6[[#This Row],[department_id]],departments[#All],2,FALSE) -> Operations | G4: =VLOOKUP(employees!$E4,departments[],3,FALSE) -> Ops | H4: 6 | I4: =VLOOKUP(employees!$H4,locations[#All],3,FALSE) -> Berlin | J4: =_xlfn.XLOOKUP(Table6[[#This Row],[City]],locations[city],locations[Continent]) -> Europe | K4: Senior | L4: Bachelor | M4: 44427 | N4: Hybrid | O4: 2.74 | P4: 6.8 | Q4: 104066.61 | R4: 43 | S4: =DATEDIF(employees!$M4, TODAY(), "y") -> 5 | T4: =VLOOKUP(employees!$H4,locations[#All],4,) -> 1.1 | U4: =employees!$Q4/employees!$T4 -> 94606.009
A5: 4 | B5: Daniel Wagner | C5: Female | D5: 25 | E5: 9 | F5: =VLOOKUP(Table6[[#This Row],[department_id]],departments[#All],2,FALSE) -> Product Management | G5: =VLOOKUP(employees!$E5,departments[],3,FALSE) -> Product | H5: 2 | I5: =VLOOKUP(employees!$H5,locations[#All],3,FALSE) -> New York | J5: =_xlfn.XLOOKUP(Table6[[#This Row],[City]],locations[city],locations[Continent]) -> North America | K5: Senior | L5: Bachelor | M5: 42662 | N5: Remote | O5: 3.92 | P5: 9.1 | Q5: 238113.44 | R5: 290 | S5: =DATEDIF(employees!$M5, TODAY(), "y") -> 9 | T5: =VLOOKUP(employees!$H5,locations[#All],4,) -> 1.3 | U5: =employees!$Q5/employees!$T5 -> 183164.18
A6: 5 | B6: Cristian Santos | C6: Male | D6: 26 | E6: 2 | F6: =VLOOKUP(Table6[[#This Row],[department_id]],departments[#All],2,FALSE) -> Data Science | G6: =VLOOKUP(employees!$E6,departments[],3,FALSE) -> Tech | H6: 8 | I6: =VLOOKUP(employees!$H6,locations[#All],3,FALSE) -> Barcelona | J6: =_xlfn.XLOOKUP(Table6[[#This Row],[City]],locations[city],locations[Continent]) -> Europe | K6: Lead | L6: Bachelor | M6: 42293 | N6: Hybrid | O6: 4.42 | P6: 5.8 | Q6: 212557.11 | R6: 1603 | S6: =DATEDIF(employees!$M6, TODAY(), "y") -> 10 | T6: =VLOOKUP(employees!$H6,locations[#All],4,) -> 1.05 | U6: =employees!$Q6/employees!$T6 -> 202435.34
A7: 6 | B7: Connie Lawrence | C7: Non-binary | D7: 35 | E7: 23 | F7: =VLOOKUP(Table6[[#This Row],[department_id]],departments[#All],2,FALSE) -> Legal | G7: =VLOOKUP(employees!$E7,departments[],3,FALSE) -> G&A | H7: 21 | I7: =VLOOKUP(employees!$H7,locations[#All],3,FALSE) -> Sydney | J7: =_xlfn.XLOOKUP(Table6[[#This Row],[City]],locations[city],locations[Continent]) -> Oceania | K7: Junior | L7: Bachelor | M7: 43041 | N7: Hybrid | O7: 4.78 | P7: 8.1 | Q7: 131834.83 | R7: 2865 | S7: =DATEDIF(employees!$M7, TODAY(), "y") -> 8 | T7: =VLOOKUP(employees!$H7,locations[#All],4,) -> 1.15 | U7: =employees!$Q7/employees!$T7 -> 114638.98
A8: 7 | B8: Abigail Shaffer | C8: Female | D8: 45 | E8: 27 | F8: =VLOOKUP(Table6[[#This Row],[department_id]],departments[#All],2,FALSE) -> Facilities | G8: =VLOOKUP(employees!$E8,departments[],3,FALSE) -> Ops | H8: 2 | I8: =VLOOKUP(employees!$H8,locations[#All],3,FALSE) -> New York | J8: =_xlfn.XLOOKUP(Table6[[#This Row],[City]],locations[city],locations[Continent]) -> North America | K8: Mid | L8: Bachelor | M8: 41902 | N8: On-site | O8: 4.67 | P8: 9.2 | Q8: 72613.77 | R8: 778 | S8: =DATEDIF(employees!$M8, TODAY(), "y") -> 11 | T8: =VLOOKUP(employees!$H8,locations[#All],4,) -> 1.3 | U8: =employees!$Q8/employees!$T8 -> 55856.746
A9: 8 | B9: Gina Moore | C9: Male | D9: 35 | E9: 13 | F9: =VLOOKUP(Table6[[#This Row],[department_id]],departments[#All],2,FALSE) -> Sales | G9: =VLOOKUP(employees!$E9,departments[],3,FALSE) -> GTM | H9: 21 | I9: =VLOOKUP(employees!$H9,locations[#All],3,FALSE) -> Sydney | J9: =_xlfn.XLOOKUP(Table6[[#This Row],[City]],locations[city],locations[Continent]) -> Oceania | K9: Mid | L9: Master | M9: 43809 | N9: Hybrid | O9: 4.22 | P9: 7.1 | Q9: 78331.79 | R9: 1834 | S9: =DATEDIF(employees!$M9, TODAY(), "y") -> 6 | T9: =VLOOKUP(employees!$H9,locations[#All],4,) -> 1.15 | U9: =employees!$Q9/employees!$T9 -> 68114.6
A10: 9 | B10: Gabrielle Davis | C10: Male | D10: 29 | E10: 5 | F10: =VLOOKUP(Table6[[#This Row],[department_id]],departments[#All],2,FALSE) -> Platform | G10: =VLOOKUP(employees!$E10,departments[],3,FALSE) -> Tech | H10: 17 | I10: =VLOOKUP(employees!$H10,locations[#All],3,FALSE) -> Mexico City | J10: =_xlfn.XLOOKUP(Table6[[#This Row],[City]],locations[city],locations[Continent]) -> South America | K10: Mid | L10: Bachelor | M10: 42025 | N10: Hybrid | O10: 3.47 | P10: 5.3 | Q10: 109102.46 | R10: 2497 | S10: =DATEDIF(employees!$M10, TODAY(), "y") -> 11 | T10: =VLOOKUP(employees!$H10,locations[#All],4,) -> 0.78 | U10: =employees!$Q10/employees!$T10 -> 139874.95
A11: 10 | B11: Ryan Munoz | C11: Non-binary | D11: 27 | E11: 17 | F11: =VLOOKUP(Table6[[#This Row],[department_id]],departments[#All],2,FALSE) -> Customer Success | G11: =VLOOKUP(employees!$E11,departments[],3,FALSE) -> GTM | H11: 9 | I11: =VLOOKUP(employees!$H11,locations[#All],3,FALSE) -> Amsterdam | J11: =_xlfn.XLOOKUP(Table6[[#This Row],[City]],locations[city],locations[Continent]) -> Europe | K11: Director | L11: Master | M11: 41734 | N11: Hybrid | O11: 3.11 | P11: 8.1 | Q11: 138649.03 | R11: 346 | S11: =DATEDIF(employees!$M11, TODAY(), "y") -> 12 | T11: =VLOOKUP(employees!$H11,locations[#All],4,) -> 1.15 | U11: =employees!$Q11/employees!$T11 -> 120564.37
A12: 11 | B12: Monica Herrera | C12: Non-binary | D12: 31 | E12: 15 | F12: =VLOOKUP(Table6[[#This Row],[department_id]],departments[#All],2,FALSE) -> Marketing | G12: =VLOOKUP(employees!$E12,departments[],3,FALSE) -> GTM | H12: 1 | I12: =VLOOKUP(employees!$H12,locations[#All],3,FALSE) -> San Francisco | J12: =_xlfn.XLOOKUP(Table6[[#This Row],[City]],locations[city],locations[Continent]) -> North America | K12: Director | L12: Bachelor | M12: 43797 | N12: On-site | O12: 3.94 | P12: 9 | Q12: 221539.35 | R12: 2411 | S12: =DATEDIF(employees!$M12, TODAY(), "y") -> 6 | T12: =VLOOKUP(employees!$H12,locations[#All],4,) -> 1.35 | U12: =employees!$Q12/employees!$T12 -> 164103.22
A13: 12 | B13: Jamie Arnold | C13: Non-binary | D13: 40 | E13: 12 | F13: =VLOOKUP(Table6[[#This Row],[department_id]],departments[#All],2,FALSE) -> UX Research | G13: =VLOOKUP(employees!$E13,departments[],3,FALSE) -> Product | H13: 6 | I13: =VLOOKUP(employees!$H13,locations[#All],3,FALSE) -> Berlin | J13: =_xlfn.XLOOKUP(Table6[[#This Row],[City]],locations[city],locations[Continent]) -> Europe | K13: Senior | L13: Bachelor | M13: 41644 | N13: On-site | O13: 3.33 | P13: 9.7 | Q13: 157508.42 | R13: 873 | S13: =DATEDIF(employees!$M13, TODAY(), "y") -> 12 | T13: =VLOOKUP(employees!$H13,locations[#All],4,) -> 1.1 | U13: =employees!$Q13/employees!$T13 -> 143189.47
... A54: 53 | B54: Crystal Robinson | C54: Female | D54: 51 | E54: 3 | F54: =VLOOKUP(Table6[[#This Row],[department_id]],departments[#All],2,FALSE) -> Data Engineering | G54: =VLOOKUP(employees!$E54,departments[],3,FALSE) -> Tech | H54: 17 | I54: =VLOOKUP(employees!$H54,locations[#All],3,FALSE) -> Mexico City | J54: =_xlfn.XLOOKUP(Table6[[#This Row],[City]],locations[city],locations[Continent]) -> South America | K54: Senior | L54: High School | M54: 41743 | N54: Remote | O54: 3.96 | P54: 9 | Q54: 137985.66 | R54: 3249 | S54: =DATEDIF(employees!$M54, TODAY(), "y") -> 12 | T54: =VLOOKUP(employees!$H54,locations[#All],4,) -> 0.78 | U54: =employees!$Q54/employees!$T54 -> 176904.69
A55: 54 | B55: Mark Perez | C55: Non-binary | D55: 54 | E55: 24 | F55: =VLOOKUP(Table6[[#This Row],[department_id]],departments[#All],2,FALSE) -> Administration | G55: =VLOOKUP(employees!$E55,departments[],3,FALSE) -> G&A | H55: 17 | I55: =VLOOKUP(employees!$H55,locations[#All],3,FALSE) -> Mexico City | J55: =_xlfn.XLOOKUP(Table6[[#This Row],[City]],locations[city],locations[Continent]) -> South America | K55: Director | L55: Master | M55: 43852 | N55: Hybrid | O55: 4.4 | P55: 7.8 | Q55: 70413.64 | R55: Unknown | S55: =DATEDIF(employees!$M55, TODAY(), "y") -> 6 | T55: =VLOOKUP(employees!$H55,locations[#All],4,) -> 0.78 | U55: =employees!$Q55/employees!$T55 -> 90273.897
A56: 55 | B56: Shannon Jones | C56: Female | D56: 56 | E56: 3 | F56: =VLOOKUP(Table6[[#This Row],[department_id]],departments[#All],2,FALSE) -> Data Engineering | G56: =VLOOKUP(employees!$E56,departments[],3,FALSE) -> Tech | H56: 9 | I56: =VLOOKUP(employees!$H56,locations[#All],3,FALSE) -> Amsterdam | J56: =_xlfn.XLOOKUP(Table6[[#This Row],[City]],locations[city],locations[Continent]) -> Europe | K56: Manager | L56: Bachelor | M56: 43637 | N56: Hybrid | O56: 2.57 | P56: 9.1 | Q56: 183975.81 | R56: 1040 | S56: =DATEDIF(employees!$M56, TODAY(), "y") -> 7 | T56: =VLOOKUP(employees!$H56,locations[#All],4,) -> 1.15 | U56: =employees!$Q56/employees!$T56 -> 159978.97
A57: 56 | B57: Michael Lewis | C57: Non-binary | D57: 20 | E57: 26 | F57: =VLOOKUP(Table6[[#This Row],[department_id]],departments[#All],2,FALSE) -> Procurement | G57: =VLOOKUP(employees!$E57,departments[],3,FALSE) -> Ops | H57: 9 | I57: =VLOOKUP(employees!$H57,locations[#All],3,FALSE) -> Amsterdam | J57: =_xlfn.XLOOKUP(Table6[[#This Row],[City]],locations[city],locations[Continent]) -> Europe | K57: Mid | L57: Bachelor | M57: 43903 | N57: On-site | O57: 3.06 | P57: 7 | Q57: 88147.69 | R57: 3408 | S57: =DATEDIF(employees!$M57, TODAY(), "y") -> 6 | T57: =VLOOKUP(employees!$H57,locations[#All],4,) -> 1.15 | U57: =employees!$Q57/employees!$T57 -> 76650.165
A58: 57 | B58: Timothy Duncan | C58: Male | D58: 25 | E58: 16 | F58: =VLOOKUP(Table6[[#This Row],[department_id]],departments[#All],2,FALSE) -> Content Marketing | G58: =VLOOKUP(employees!$E58,departments[],3,FALSE) -> GTM | H58: 21 | I58: =VLOOKUP(employees!$H58,locations[#All],3,FALSE) -> Sydney | J58: =_xlfn.XLOOKUP(Table6[[#This Row],[City]],locations[city],locations[Continent]) -> Oceania | K58: Senior | L58: Bachelor | M58: 45311 | N58: Hybrid | O58: 3.06 | P58: 8.2 | Q58: 94763.13 | R58: 3452 | S58: =DATEDIF(employees!$M58, TODAY(), "y") -> 2 | T58: =VLOOKUP(employees!$H58,locations[#All],4,) -> 1.15 | U58: =employees!$Q58/employees!$T58 -> 82402.722
A59: 58 | B59: Richard Aguirre | C59: Female | D59: 64 | E59: 12 | F59: =VLOOKUP(Table6[[#This Row],[department_id]],departments[#All],2,FALSE) -> UX Research | G59: =VLOOKUP(employees!$E59,departments[],3,FALSE) -> Product | H59: 14 | I59: =VLOOKUP(employees!$H59,locations[#All],3,FALSE) -> Dubai | J59: =_xlfn.XLOOKUP(Table6[[#This Row],[City]],locations[city],locations[Continent]) -> Asia | K59: Vp | L59: Bachelor | M59: 44349 | N59: On-site | O59: 3.03 | P59: 8.5 | Q59: 307354.7 | R59: Unknown | S59: =DATEDIF(employees!$M59, TODAY(), "y") -> 5 | T59: =VLOOKUP(employees!$H59,locations[#All],4,) -> 1.05 | U59: =employees!$Q59/employees!$T59 -> 292718.76
A60: 59 | B60: Brent Jordan | C60: Female | D60: 57 | E60: 25 | F60: =VLOOKUP(Table6[[#This Row],[department_id]],departments[#All],2,FALSE) -> Operations | G60: =VLOOKUP(employees!$E60,departments[],3,FALSE) -> Ops | H60: 6 | I60: =VLOOKUP(employees!$H60,locations[#All],3,FALSE) -> Berlin | J60: =_xlfn.XLOOKUP(Table6[[#This Row],[City]],locations[city],locations[Continent]) -> Europe | K60: Junior | L60: PhD | M60: 45606 | N60: Hybrid | O60: 3.15 | P60: 5.5 | Q60: 48276.76 | R60: 3093 | S60: =DATEDIF(employees!$M60, TODAY(), "y") -> 1 | T60: =VLOOKUP(employees!$H60,locations[#All],4,) -> 1.1 | U60: =employees!$Q60/employees!$T60 -> 43887.964
A61: 60 | B61: John Daniel | C61: Female | D61: 22 | E61: 6 | F61: =VLOOKUP(Table6[[#This Row],[department_id]],departments[#All],2,FALSE) -> Security | G61: =VLOOKUP(employees!$E61,departments[],3,FALSE) -> Tech | H61: 10 | I61: =VLOOKUP(employees!$H61,locations[#All],3,FALSE) -> Warsaw | J61: =_xlfn.XLOOKUP(Table6[[#This Row],[City]],locations[city],locations[Continent]) -> Europe | K61: Intern | L61: PhD | M61: 42676 | N61: Hybrid | O61: 4.1 | P61: 5.6 | Q61: 66078.07 | R61: 2919 | S61: =DATEDIF(employees!$M61, TODAY(), "y") -> 9 | T61: =VLOOKUP(employees!$H61,locations[#All],4,) -> 0.95 | U61: =employees!$Q61/employees!$T61 -> 69555.863
A62: 61 | B62: Victoria Garcia | C62: Female | D62: 41 | E62: 1 | F62: =VLOOKUP(Table6[[#This Row],[department_id]],departments[#All],2,FALSE) -> Engineering | G62: =VLOOKUP(employees!$E62,departments[],3,FALSE) -> Tech | H62: 19 | I62: =VLOOKUP(employees!$H62,locations[#All],3,FALSE) -> Tokyo | J62: =_xlfn.XLOOKUP(Table6[[#This Row],[City]],locations[city],locations[Continent]) -> Asia | K62: Mid | L62: Bachelor | M62: 45561 | N62: On-site | O62: 4.66 | P62: 7.3 | Q62: 159527.03 | R62: 1215 | S62: =DATEDIF(employees!$M62, TODAY(), "y") -> 1 | T62: =VLOOKUP(employees!$H62,locations[#All],4,) -> 1.2 | U62: =employees!$Q62/employees!$T62 -> 132939.19
A63: 62 | B63: Gerald Hensley | C63: Male | D63: 29 | E63: 3 | F63: =VLOOKUP(Table6[[#This Row],[department_id]],departments[#All],2,FALSE) -> Data Engineering | G63: =VLOOKUP(employees!$E63,departments[],3,FALSE) -> Tech | H63: 19 | I63: =VLOOKUP(employees!$H63,locations[#All],3,FALSE) -> Tokyo | J63: =_xlfn.XLOOKUP(Table6[[#This Row],[City]],locations[city],locations[Continent]) -> Asia | K63: Senior | L63: Master | M63: 42079 | N63: Remote | O63: 2.7 | P63: 6.2 | Q63: 194246.36 | R63: 903 | S63: =DATEDIF(employees!$M63, TODAY(), "y") -> 11 | T63: =VLOOKUP(employees!$H63,locations[#All],4,) -> 1.2 | U63: =employees!$Q63/employees!$T63 -> 161871.97
A64: 63 | B64: Connor West | C64: Female | D64: 48 | E64: 20 | F64: =VLOOKUP(Table6[[#This Row],[department_id]],departments[#All],2,FALSE) -> Recruiting | G64: =VLOOKUP(employees!$E64,departments[],3,FALSE) -> G&A | H64: 20 | I64: =VLOOKUP(employees!$H64,locations[#All],3,FALSE) -> Singapore | J64: =_xlfn.XLOOKUP(Table6[[#This Row],[City]],locations[city],locations[Continent]) -> Asia | K64: Mid | L64: Master | M64: 45920 | N64: On-site | O64: 3.85 | P64: 7.1 | Q64: 78854.41 | R64: 997 | S64: =DATEDIF(employees!$M64, TODAY(), "y") -> 0 | T64: =VLOOKUP(employees!$H64,locations[#All],4,) -> 1.22 | U64: =employees!$Q64/employees!$T64 -> 64634.762
A65: 64 | B65: Donald Wright | C65: Non-binary | D65: 33 | E65: 24 | F65: =VLOOKUP(Table6[[#This Row],[department_id]],departments[#All],2,FALSE) -> Administration | G65: =VLOOKUP(employees!$E65,departments[],3,FALSE) -> G&A | H65: 4 | I65: =VLOOKUP(employees!$H65,locations[#All],3,FALSE) -> Toronto | J65: =_xlfn.XLOOKUP(Table6[[#This Row],[City]],locations[city],locations[Continent]) -> North America | K65: Manager | L65: Bachelor | M65: 43342 | N65: On-site | O65: 3.05 | P65: 7.6 | Q65: 77825.29 | R65: 311 | S65: =DATEDIF(employees!$M65, TODAY(), "y") -> 8 | T65: =VLOOKUP(employees!$H65,locations[#All],4,) -> 1.1 | U65: =employees!$Q65/employees!$T65 -> 70750.264
A66: 65 | B66: Jessica Callahan | C66: Male | D66: 38 | E66: 23 | F66: =VLOOKUP(Table6[[#This Row],[department_id]],departments[#All],2,FALSE) -> Legal | G66: =VLOOKUP(employees!$E66,departments[],3,FALSE) -> G&A | H66: 20 | I66: =VLOOKUP(employees!$H66,locations[#All],3,FALSE) -> Singapore | J66: =_xlfn.XLOOKUP(Table6[[#This Row],[City]],locations[city],locations[Continent]) -> Asia | K66: Mid | L66: Master | M66: 41907 | N66: Hybrid | O66: 3.54 | P66: 8.3 | Q66: 236083.96 | R66: 3227 | S66: =DATEDIF(employees!$M66, TODAY(), "y") -> 11 | T66: =VLOOKUP(employees!$H66,locations[#All],4,) -> 1.22 | U66: =employees!$Q66/employees!$T66 -> 193511.44
A67: 66 | B67: Amber Kidd | C67: Female | D67: 27 | E67: 21 | F67: =VLOOKUP(Table6[[#This Row],[department_id]],departments[#All],2,FALSE) -> Finance | G67: =VLOOKUP(employees!$E67,departments[],3,FALSE) -> G&A | H67: 19 | I67: =VLOOKUP(employees!$H67,locations[#All],3,FALSE) -> Tokyo | J67: =_xlfn.XLOOKUP(Table6[[#This Row],[City]],locations[city],locations[Continent]) -> Asia | K67: Senior | L67: Bachelor | M67: 43260 | N67: Hybrid | O67: 4.59 | P67: 9 | Q67: 90725.7 | R67: 1229 | S67: =DATEDIF(employees!$M67, TODAY(), "y") -> 8 | T67: =VLOOKUP(employees!$H67,locations[#All],4,) -> 1.2 | U67: =employees!$Q67/employees!$T67 -> 75604.75
A68: 67 | B68: Tracy House | C68: Female | D68: 27 | E68: 10 | F68: =VLOOKUP(Table6[[#This Row],[department_id]],departments[#All],2,FALSE) -> Product Operations | G68: =VLOOKUP(employees!$E68,departments[],3,FALSE) -> Product | H68: 20 | I68: =VLOOKUP(employees!$H68,locations[#All],3,FALSE) -> Singapore | J68: =_xlfn.XLOOKUP(Table6[[#This Row],[City]],locations[city],locations[Continent]) -> Asia | K68: Senior | L68: Bachelor | M68: 44004 | N68: On-site | O68: 3.43 | P68: 6.3 | Q68: 147750.11 | R68: 2653 | S68: =DATEDIF(employees!$M68, TODAY(), "y") -> 6 | T68: =VLOOKUP(employees!$H68,locations[#All],4,) -> 1.22 | U68: =employees!$Q68/employees!$T68 -> 121106.65
A69: 68 | B69: Carol Tucker | C69: Non-binary | D69: 36 | E69: 20 | F69: =VLOOKUP(Table6[[#This Row],[department_id]],departments[#All],2,FALSE) -> Recruiting | G69: =VLOOKUP(employees!$E69,departments[],3,FALSE) -> G&A | H69: 2 | I69: =VLOOKUP(employees!$H69,locations[#All],3,FALSE) -> New York | J69: =_xlfn.XLOOKUP(Table6[[#This Row],[City]],locations[city],locations[Continent]) -> North America | K69: Manager | L69: High School | M69: 44280 | N69: On-site | O69: 4.05 | P69: 9.1 | Q69: 154264.95 | R69: 1826 | S69: =DATEDIF(employees!$M69, TODAY(), "y") -> 5 | T69: =VLOOKUP(employees!$H69,locations[#All],4,) -> 1.3 | U69: =employees!$Q69/employees!$T69 -> 118665.35
A70: 69 | B70: James Brown | C70: Female | D70: 53 | E70: 25 | F70: =VLOOKUP(Table6[[#This Row],[department_id]],departments[#All],2,FALSE) -> Operations | G70: =VLOOKUP(employees!$E70,departments[],3,FALSE) -> Ops | H70: 9 | I70: =VLOOKUP(employees!$H70,locations[#All],3,FALSE) -> Amsterdam | J70: =_xlfn.XLOOKUP(Table6[[#This Row],[City]],locations[city],locations[Continent]) -> Europe | K70: Senior | L70: Bachelor | M70: 43075 | N70: Remote | O70: 2.92 | P70: 7.8 | Q70: 139128.18 | R70: 3194 | S70: =DATEDIF(employees!$M70, TODAY(), "y") -> 8 | T70: =VLOOKUP(employees!$H70,locations[#All],4,) -> 1.15 | U70: =employees!$Q70/employees!$T70 -> 120981.03
A71: 70 | B71: William Baker | C71: Female | D71: 62 | E71: 3 | F71: =VLOOKUP(Table6[[#This Row],[department_id]],departments[#All],2,FALSE) -> Data Engineering | G71: =VLOOKUP(employees!$E71,departments[],3,FALSE) -> Tech | H71: 16 | I71: =VLOOKUP(employees!$H71,locations[#All],3,FALSE) -> São Paulo | J71: =_xlfn.XLOOKUP(Table6[[#This Row],[City]],locations[city],locations[Continent]) -> South America | K71: Mid | L71: High School | M71: 44370 | N71: On-site | O71: 3.45 | P71: 7.4 | Q71: 100919.5 | R71: 2835 | S71: =DATEDIF(employees!$M71, TODAY(), "y") -> 5 | T71: =VLOOKUP(employees!$H71,locations[#All],4,) -> 0.8 | U71: =employees!$Q71/employees!$T71 -> 126149.38
... A74: 73 | B74: Brittney Phillips | C74: Male | D74: 21 | E74: 10 | F74: =VLOOKUP(Table6[[#This Row],[department_id]],departments[#All],2,FALSE) -> Product Operations | G74: =VLOOKUP(employees!$E74,departments[],3,FALSE) -> Product | H74: 15 | I74: =VLOOKUP(employees!$H74,locations[#All],3,FALSE) -> Cape Town | J74: =_xlfn.XLOOKUP(Table6[[#This Row],[City]],locations[city],locations[Continent]) -> Africa | K74: Manager | L74: PhD | M74: 45610 | N74: Hybrid | O74: 3.05 | P74: 5.8 | Q74: 122346.59 | R74: 3239 | S74: =DATEDIF(employees!$M74, TODAY(), "y") -> 1 | T74: =VLOOKUP(employees!$H74,locations[#All],4,) -> 0.7 | U74: =employees!$Q74/employees!$T74 -> 174780.84
A75: 74 | B75: Lauren Daniels | C75: Female | D75: 27 | E75: 3 | F75: =VLOOKUP(Table6[[#This Row],[department_id]],departments[#All],2,FALSE) -> Data Engineering | G75: =VLOOKUP(employees!$E75,departments[],3,FALSE) -> Tech | H75: 8 | I75: =VLOOKUP(employees!$H75,locations[#All],3,FALSE) -> Barcelona | J75: =_xlfn.XLOOKUP(Table6[[#This Row],[City]],locations[city],locations[Continent]) -> Europe | K75: Vp | L75: Bachelor | M75: 42569 | N75: On-site | O75: 4.65 | P75: 6.4 | Q75: 408984.32 | R75: Unknown | S75: =DATEDIF(employees!$M75, TODAY(), "y") -> 10 | T75: =VLOOKUP(employees!$H75,locations[#All],4,) -> 1.05 | U75: =employees!$Q75/employees!$T75 -> 389508.88
A76: 75 | B76: Amy Silva | C76: Female | D76: 32 | E76: 16 | F76: =VLOOKUP(Table6[[#This Row],[department_id]],departments[#All],2,FALSE) -> Content Marketing | G76: =VLOOKUP(employees!$E76,departments[],3,FALSE) -> GTM | H76: 16 | I76: =VLOOKUP(employees!$H76,locations[#All],3,FALSE) -> São Paulo | J76: =_xlfn.XLOOKUP(Table6[[#This Row],[City]],locations[city],locations[Continent]) -> South America | K76: Mid | L76: Master | M76: 42824 | N76: Hybrid | O76: 4.52 | P76: 9.1 | Q76: 50041.46 | R76: 1278 | S76: =DATEDIF(employees!$M76, TODAY(), "y") -> 9 | T76: =VLOOKUP(employees!$H76,locations[#All],4,) -> 0.8 | U76: =employees!$Q76/employees!$T76 -> 62551.825
A77: 76 | B77: Sarah Moore | C77: Female | D77: 20 | E77: 14 | F77: =VLOOKUP(Table6[[#This Row],[department_id]],departments[#All],2,FALSE) -> Sales Operations | G77: =VLOOKUP(employees!$E77,departments[],3,FALSE) -> GTM | H77: 11 | I77: =VLOOKUP(employees!$H77,locations[#All],3,FALSE) -> Bengaluru | J77: =_xlfn.XLOOKUP(Table6[[#This Row],[City]],locations[city],locations[Continent]) -> Asia | K77: Manager | L77: Bachelor | M77: 45799 | N77: On-site | O77: 3.85 | P77: 9.8 | Q77: 88461.29 | R77: 2909 | S77: =DATEDIF(employees!$M77, TODAY(), "y") -> 1 | T77: =VLOOKUP(employees!$H77,locations[#All],4,) -> 0.7 | U77: =employees!$Q77/employees!$T77 -> 126373.27
A78: 77 | B78: Angela Lopez | C78: Female | D78: 40 | E78: 18 | F78: =VLOOKUP(Table6[[#This Row],[department_id]],departments[#All],2,FALSE) -> Customer Support | G78: =VLOOKUP(employees!$E78,departments[],3,FALSE) -> GTM | H78: 16 | I78: =VLOOKUP(employees!$H78,locations[#All],3,FALSE) -> São Paulo | J78: =_xlfn.XLOOKUP(Table6[[#This Row],[City]],locations[city],locations[Continent]) -> South America | K78: Mid | L78: Master | M78: 44730 | N78: Remote | O78: 3.05 | P78: 6.8 | Q78: 50113.61 | R78: 1584 | S78: =DATEDIF(employees!$M78, TODAY(), "y") -> 4 | T78: =VLOOKUP(employees!$H78,locations[#All],4,) -> 0.8 | U78: =employees!$Q78/employees!$T78 -> 62642.012
A79: 78 | B79: Megan Young | C79: Female | D79: 62 | E79: 11 | F79: =VLOOKUP(Table6[[#This Row],[department_id]],departments[#All],2,FALSE) -> Design | G79: =VLOOKUP(employees!$E79,departments[],3,FALSE) -> Product | H79: 16 | I79: =VLOOKUP(employees!$H79,locations[#All],3,FALSE) -> São Paulo | J79: =_xlfn.XLOOKUP(Table6[[#This Row],[City]],locations[city],locations[Continent]) -> South America | K79: Senior | L79: Master | M79: 44763 | N79: Hybrid | O79: 2.85 | P79: 9.6 | Q79: 86565.5 | R79: 2989 | S79: =DATEDIF(employees!$M79, TODAY(), "y") -> 4 | T79: =VLOOKUP(employees!$H79,locations[#All],4,) -> 0.8 | U79: =employees!$Q79/employees!$T79 -> 108206.88
A80: 79 | B80: Steve Sanchez | C80: Male | D80: 53 | E80: 11 | F80: =VLOOKUP(Table6[[#This Row],[department_id]],departments[#All],2,FALSE) -> Design | G80: =VLOOKUP(employees!$E80,departments[],3,FALSE) -> Product | H80: 4 | I80: =VLOOKUP(employees!$H80,locations[#All],3,FALSE) -> Toronto | J80: =_xlfn.XLOOKUP(Table6[[#This Row],[City]],locations[city],locations[Continent]) -> North America | K80: Manager | L80: Master | M80: 45246 | N80: On-site | O80: 2.83 | P80: 9.2 | Q80: 199624.81 | R80: 3283 | S80: =DATEDIF(employees!$M80, TODAY(), "y") -> 2 | T80: =VLOOKUP(employees!$H80,locations[#All],4,) -> 1.1 | U80: =employees!$Q80/employees!$T80 -> 181477.1
A81: 80 | B81: Lisa Barnes | C81: Non-binary | D81: 25 | E81: 26 | F81: =VLOOKUP(Table6[[#This Row],[department_id]],departments[#All],2,FALSE) -> Procurement | G81: =VLOOKUP(employees!$E81,departments[],3,FALSE) -> Ops | H81: 9 | I81: =VLOOKUP(employees!$H81,locations[#All],3,FALSE) -> Amsterdam | J81: =_xlfn.XLOOKUP(Table6[[#This Row],[City]],locations[city],locations[Continent]) -> Europe | K81: Mid | L81: Master | M81: 44896 | N81: Remote | O81: 4.48 | P81: 6.8 | Q81: 90564.63 | R81: 1135 | S81: =DATEDIF(employees!$M81, TODAY(), "y") -> 3 | T81: =VLOOKUP(employees!$H81,locations[#All],4,) -> 1.15 | U81: =employees!$Q81/employees!$T81 -> 78751.852
A82: 81 | B82: Kelly Donovan | C82: Non-binary | D82: 24 | E82: 25 | F82: =VLOOKUP(Table6[[#This Row],[department_id]],departments[#All],2,FALSE) -> Operations | G82: =VLOOKUP(employees!$E82,departments[],3,FALSE) -> Ops | H82: 16 | I82: =VLOOKUP(employees!$H82,locations[#All],3,FALSE) -> São Paulo | J82: =_xlfn.XLOOKUP(Table6[[#This Row],[City]],locations[city],locations[Continent]) -> South America | K82: Manager | L82: Bachelor | M82: 41934 | N82: Hybrid | O82: 3.16 | P82: 6.1 | Q82: 105739.18 | R82: 3466 | S82: =DATEDIF(employees!$M82, TODAY(), "y") -> 11 | T82: =VLOOKUP(employees!$H82,locations[#All],4,) -> 0.8 | U82: =employees!$Q82/employees!$T82 -> 132173.97
A83: 82 | B83: Mike Allen | C83: Female | D83: 30 | E83: 25 | F83: =VLOOKUP(Table6[[#This Row],[department_id]],departments[#All],2,FALSE) -> Operations | G83: =VLOOKUP(employees!$E83,departments[],3,FALSE) -> Ops | H83: 21 | I83: =VLOOKUP(employees!$H83,locations[#All],3,FALSE) -> Sydney | J83: =_xlfn.XLOOKUP(Table6[[#This Row],[City]],locations[city],locations[Continent]) -> Oceania | K83: Senior | L83: Master | M83: 42463 | N83: Remote | O83: 2.61 | P83: 8.8 | Q83: 104908.55 | R83: 3194 | S83: =DATEDIF(employees!$M83, TODAY(), "y") -> 10 | T83: =VLOOKUP(employees!$H83,locations[#All],4,) -> 1.15 | U83: =employees!$Q83/employees!$T83 -> 91224.826
A84: 83 | B84: Michael Evans | C84: Male | D84: 31 | E84: 5 | F84: =VLOOKUP(Table6[[#This Row],[department_id]],departments[#All],2,FALSE) -> Platform | G84: =VLOOKUP(employees!$E84,departments[],3,FALSE) -> Tech | H84: 8 | I84: =VLOOKUP(employees!$H84,locations[#All],3,FALSE) -> Barcelona | J84: =_xlfn.XLOOKUP(Table6[[#This Row],[City]],locations[city],locations[Continent]) -> Europe | K84: Senior | L84: High School | M84: 43115 | N84: Remote | O84: 3.93 | P84: 6.2 | Q84: 187008.85 | R84: 1243 | S84: =DATEDIF(employees!$M84, TODAY(), "y") -> 8 | T84: =VLOOKUP(employees!$H84,locations[#All],4,) -> 1.05 | U84: =employees!$Q84/employees!$T84 -> 178103.67
A85: 84 | B85: Paul Jones | C85: Non-binary | D85: 20 | E85: 15 | F85: =VLOOKUP(Table6[[#This Row],[department_id]],departments[#All],2,FALSE) -> Marketing | G85: =VLOOKUP(employees!$E85,departments[],3,FALSE) -> GTM | H85: 21 | I85: =VLOOKUP(employees!$H85,locations[#All],3,FALSE) -> Sydney | J85: =_xlfn.XLOOKUP(Table6[[#This Row],[City]],locations[city],locations[Continent]) -> Oceania | K85: Mid | L85: Master | M85: 43731 | N85: Hybrid | O85: 3.16 | P85: 7.6 | Q85: 80018.24 | R85: 626 | S85: =DATEDIF(employees!$M85, TODAY(), "y") -> 6 | T85: =VLOOKUP(employees!$H85,locations[#All],4,) -> 1.15 | U85: =employees!$Q85/employees!$T85 -> 69581.078
A86: 85 | B86: Zachary Ferrell | C86: Non-binary | D86: 36 | E86: 19 | F86: =VLOOKUP(Table6[[#This Row],[department_id]],departments[#All],2,FALSE) -> Human Resources | G86: =VLOOKUP(employees!$E86,departments[],3,FALSE) -> G&A | H86: 10 | I86: =VLOOKUP(employees!$H86,locations[#All],3,FALSE) -> Warsaw | J86: =_xlfn.XLOOKUP(Table6[[#This Row],[City]],locations[city],locations[Continent]) -> Europe | K86: Senior | L86: Bachelor | M86: 45115 | N86: On-site | O86: 4.8 | P86: 9.1 | Q86: 67596.59 | R86: 1967 | S86: =DATEDIF(employees!$M86, TODAY(), "y") -> 3 | T86: =VLOOKUP(employees!$H86,locations[#All],4,) -> 0.95 | U86: =employees!$Q86/employees!$T86 -> 71154.305
A87: 86 | B87: Daniel Baker | C87: Male | D87: 62 | E87: 12 | F87: =VLOOKUP(Table6[[#This Row],[department_id]],departments[#All],2,FALSE) -> UX Research | G87: =VLOOKUP(employees!$E87,departments[],3,FALSE) -> Product | H87: 19 | I87: =VLOOKUP(employees!$H87,locations[#All],3,FALSE) -> Tokyo | J87: =_xlfn.XLOOKUP(Table6[[#This Row],[City]],locations[city],locations[Continent]) -> Asia | K87: Mid | L87: Bachelor | M87: 44058 | N87: On-site | O87: 4.49 | P87: 8.7 | Q87: 179409.73 | R87: 2198 | S87: =DATEDIF(employees!$M87, TODAY(), "y") -> 6 | T87: =VLOOKUP(employees!$H87,locations[#All],4,) -> 1.2 | U87: =employees!$Q87/employees!$T87 -> 149508.11
... A203: 202 | B203: Ricky Davis Ii | C203: Female | D203: 55 | E203: 21 | F203: =VLOOKUP(Table6[[#This Row],[department_id]],departments[#All],2,FALSE) -> Finance | G203: =VLOOKUP(employees!$E203,departments[],3,FALSE) -> G&A | H203: 2 | I203: =VLOOKUP(employees!$H203,locations[#All],3,FALSE) -> New York | J203: =_xlfn.XLOOKUP(Table6[[#This Row],[City]],locations[city],locations[Continent]) -> North America | K203: Junior | L203: Bachelor | M203: 44746 | N203: Hybrid | O203: 4.12 | P203: 5.4 | Q203: 118568.84 | R203: 2065 | S203: =DATEDIF(employees!$M203, TODAY(), "y") -> 4 | T203: =VLOOKUP(employees!$H203,locations[#All],4,) -> 1.3 | U203: =employees!$Q203/employees!$T203 -> 91206.8
A204: 203 | B204: Elizabeth Perkins | C204: Non-binary | D204: 22 | E204: 11 | F204: =VLOOKUP(Table6[[#This Row],[department_id]],departments[#All],2,FALSE) -> Design | G204: =VLOOKUP(employees!$E204,departments[],3,FALSE) -> Product | H204: 19 | I204: =VLOOKUP(employees!$H204,locations[#All],3,FALSE) -> Tokyo | J204: =_xlfn.XLOOKUP(Table6[[#This Row],[City]],locations[city],locations[Continent]) -> Asia | K204: Director | L204: Bachelor | M204: 42421 | N204: Remote | O204: 4.09 | P204: 7.7 | Q204: 240854.11 | R204: Unknown | S204: =DATEDIF(employees!$M204, TODAY(), "y") -> 10 | T204: =VLOOKUP(employees!$H204,locations[#All],4,) -> 1.2 | U204: =employees!$Q204/employees!$T204 -> 200711.76
A205: 204 | B205: Joseph Coleman | C205: Male | D205: 40 | E205: 22 | F205: =VLOOKUP(Table6[[#This Row],[department_id]],departments[#All],2,FALSE) -> Accounting | G205: =VLOOKUP(employees!$E205,departments[],3,FALSE) -> G&A | H205: 9 | I205: =VLOOKUP(employees!$H205,locations[#All],3,FALSE) -> Amsterdam | J205: =_xlfn.XLOOKUP(Table6[[#This Row],[City]],locations[city],locations[Continent]) -> Europe | K205: Manager | L205: High School | M205: 41909 | N205: On-site | O205: 2.83 | P205: 8.9 | Q205: 216697.08 | R205: 554 | S205: =DATEDIF(employees!$M205, TODAY(), "y") -> 11 | T205: =VLOOKUP(employees!$H205,locations[#All],4,) -> 1.15 | U205: =employees!$Q205/employees!$T205 -> 188432.24
A206: 205 | B206: Erin Warner | C206: Non-binary | D206: 54 | E206: 10 | F206: =VLOOKUP(Table6[[#This Row],[department_id]],departments[#All],2,FALSE) -> Product Operations | G206: =VLOOKUP(employees!$E206,departments[],3,FALSE) -> Product | H206: 6 | I206: =VLOOKUP(employees!$H206,locations[#All],3,FALSE) -> Berlin | J206: =_xlfn.XLOOKUP(Table6[[#This Row],[City]],locations[city],locations[Continent]) -> Europe | K206: Senior | L206: Bachelor | M206: 44827 | N206: Hybrid | O206: 2.82 | P206: 9.7 | Q206: 150341.81 | R206: 384 | S206: =DATEDIF(employees!$M206, TODAY(), "y") -> 3 | T206: =VLOOKUP(employees!$H206,locations[#All],4,) -> 1.1 | U206: =employees!$Q206/employees!$T206 -> 136674.37
A207: 206 | B207: David Martinez | C207: Male | D207: 41 | E207: 12 | F207: =VLOOKUP(Table6[[#This Row],[department_id]],departments[#All],2,FALSE) -> UX Research | G207: =VLOOKUP(employees!$E207,departments[],3,FALSE) -> Product | H207: 2 | I207: =VLOOKUP(employees!$H207,locations[#All],3,FALSE) -> New York | J207: =_xlfn.XLOOKUP(Table6[[#This Row],[City]],locations[city],locations[Continent]) -> North America | K207: Junior | L207: Bachelor | M207: 43541 | N207: Hybrid | O207: 3.87 | P207: 9.7 | Q207: 92028.92 | R207: 30 | S207: =DATEDIF(employees!$M207, TODAY(), "y") -> 7 | T207: =VLOOKUP(employees!$H207,locations[#All],4,) -> 1.3 | U207: =employees!$Q207/employees!$T207 -> 70791.477
A208: 207 | B208: Bryan Herrera | C208: Non-binary | D208: 44 | E208: 26 | F208: =VLOOKUP(Table6[[#This Row],[department_id]],departments[#All],2,FALSE) -> Procurement | G208: =VLOOKUP(employees!$E208,departments[],3,FALSE) -> Ops | H208: 15 | I208: =VLOOKUP(employees!$H208,locations[#All],3,FALSE) -> Cape Town | J208: =_xlfn.XLOOKUP(Table6[[#This Row],[City]],locations[city],locations[Continent]) -> Africa | K208: Mid | L208: Bachelor | M208: 44554 | N208: Hybrid | O208: 4.02 | P208: 5.4 | Q208: 69746.24 | R208: 1368 | S208: =DATEDIF(employees!$M208, TODAY(), "y") -> 4 | T208: =VLOOKUP(employees!$H208,locations[#All],4,) -> 0.7 | U208: =employees!$Q208/employees!$T208 -> 99637.486
A209: 208 | B209: Cathy Robinson | C209: Female | D209: 65 | E209: 23 | F209: =VLOOKUP(Table6[[#This Row],[department_id]],departments[#All],2,FALSE) -> Legal | G209: =VLOOKUP(employees!$E209,departments[],3,FALSE) -> G&A | H209: 3 | I209: =VLOOKUP(employees!$H209,locations[#All],3,FALSE) -> Austin | J209: =_xlfn.XLOOKUP(Table6[[#This Row],[City]],locations[city],locations[Continent]) -> North America | K209: Junior | L209: Master | M209: 42903 | N209: On-site | O209: 3.4 | P209: 6.7 | Q209: 95279.69 | R209: 1523 | S209: =DATEDIF(employees!$M209, TODAY(), "y") -> 9 | T209: =VLOOKUP(employees!$H209,locations[#All],4,) -> 1.05 | U209: =employees!$Q209/employees!$T209 -> 90742.562
A210: 209 | B210: Dr. William Warren | C210: Male | D210: 25 | E210: 15 | F210: =VLOOKUP(Table6[[#This Row],[department_id]],departments[#All],2,FALSE) -> Marketing | G210: =VLOOKUP(employees!$E210,departments[],3,FALSE) -> GTM | H210: 12 | I210: =VLOOKUP(employees!$H210,locations[#All],3,FALSE) -> Hyderabad | J210: =_xlfn.XLOOKUP(Table6[[#This Row],[City]],locations[city],locations[Continent]) -> Asia | K210: Lead | L210: Bachelor | M210: 42477 | N210: Hybrid | O210: 3.78 | P210: 7 | Q210: 59629.94 | R210: 3472 | S210: =DATEDIF(employees!$M210, TODAY(), "y") -> 10 | T210: =VLOOKUP(employees!$H210,locations[#All],4,) -> 0.68 | U210: =employees!$Q210/employees!$T210 -> 87691.088
A211: 210 | B211: Brian Lee | C211: Female | D211: 20 | E211: 3 | F211: =VLOOKUP(Table6[[#This Row],[department_id]],departments[#All],2,FALSE) -> Data Engineering | G211: =VLOOKUP(employees!$E211,departments[],3,FALSE) -> Tech | H211: 20 | I211: =VLOOKUP(employees!$H211,locations[#All],3,FALSE) -> Singapore | J211: =_xlfn.XLOOKUP(Table6[[#This Row],[City]],locations[city],locations[Continent]) -> Asia | K211: Senior | L211: Bachelor | M211: 44297 | N211: Hybrid | O211: 2.69 | P211: 9.3 | Q211: 291094.24 | R211: 1912 | S211: =DATEDIF(employees!$M211, TODAY(), "y") -> 5 | T211: =VLOOKUP(employees!$H211,locations[#All],4,) -> 1.22 | U211: =employees!$Q211/employees!$T211 -> 238601.84
A212: 211 | B212: Christopher Smith | C212: Male | D212: 28 | E212: 19 | F212: =VLOOKUP(Table6[[#This Row],[department_id]],departments[#All],2,FALSE) -> Human Resources | G212: =VLOOKUP(employees!$E212,departments[],3,FALSE) -> G&A | H212: 17 | I212: =VLOOKUP(employees!$H212,locations[#All],3,FALSE) -> Mexico City | J212: =_xlfn.XLOOKUP(Table6[[#This Row],[City]],locations[city],locations[Continent]) -> South America | K212: Junior | L212: Bachelor | M212: 44758 | N212: On-site | O212: 2.84 | P212: 5.8 | Q212: 34332.44 | R212: 1157 | S212: =DATEDIF(employees!$M212, TODAY(), "y") -> 4 | T212: =VLOOKUP(employees!$H212,locations[#All],4,) -> 0.78 | U212: =employees!$Q212/employees!$T212 -> 44015.949
A213: 212 | B213: Denise Mccann | C213: Non-binary | D213: 60 | E213: 26 | F213: =VLOOKUP(Table6[[#This Row],[department_id]],departments[#All],2,FALSE) -> Procurement | G213: =VLOOKUP(employees!$E213,departments[],3,FALSE) -> Ops | H213: 3 | I213: =VLOOKUP(employees!$H213,locations[#All],3,FALSE) -> Austin | J213: =_xlfn.XLOOKUP(Table6[[#This Row],[City]],locations[city],locations[Continent]) -> North America | K213: Mid | L213: Bachelor | M213: 43660 | N213: Hybrid | O213: 3.55 | P213: 5.7 | Q213: 55714.99 | R213: 880 | S213: =DATEDIF(employees!$M213, TODAY(), "y") -> 7 | T213: =VLOOKUP(employees!$H213,locations[#All],4,) -> 1.05 | U213: =employees!$Q213/employees!$T213 -> 53061.895
A214: 213 | B214: Melissa Martinez | C214: Female | D214: 41 | E214: 27 | F214: =VLOOKUP(Table6[[#This Row],[department_id]],departments[#All],2,FALSE) -> Facilities | G214: =VLOOKUP(employees!$E214,departments[],3,FALSE) -> Ops | H214: 20 | I214: =VLOOKUP(employees!$H214,locations[#All],3,FALSE) -> Singapore | J214: =_xlfn.XLOOKUP(Table6[[#This Row],[City]],locations[city],locations[Continent]) -> Asia | K214: Mid | L214: Bachelor | M214: 44339 | N214: Remote | O214: 4 | P214: 7.9 | Q214: 66081.21 | R214: 1457 | S214: =DATEDIF(employees!$M214, TODAY(), "y") -> 5 | T214: =VLOOKUP(employees!$H214,locations[#All],4,) -> 1.22 | U214: =employees!$Q214/employees!$T214 -> 54164.926
A215: 214 | B215: Katherine Salas | C215: Female | D215: 40 | E215: 23 | F215: =VLOOKUP(Table6[[#This Row],[department_id]],departments[#All],2,FALSE) -> Legal | G215: =VLOOKUP(employees!$E215,departments[],3,FALSE) -> G&A | H215: 7 | I215: =VLOOKUP(employees!$H215,locations[#All],3,FALSE) -> Paris | J215: =_xlfn.XLOOKUP(Table6[[#This Row],[City]],locations[city],locations[Continent]) -> Europe | K215: Mid | L215: Bachelor | M215: 43095 | N215: Hybrid | O215: 3.63 | P215: 7.8 | Q215: 129651.98 | R215: 1786 | S215: =DATEDIF(employees!$M215, TODAY(), "y") -> 8 | T215: =VLOOKUP(employees!$H215,locations[#All],4,) -> 1.18 | U215: =employees!$Q215/employees!$T215 -> 109874.56
A216: 215 | B216: Julie Alexander | C216: Non-binary | D216: 54 | E216: 27 | F216: =VLOOKUP(Table6[[#This Row],[department_id]],departments[#All],2,FALSE) -> Facilities | G216: =VLOOKUP(employees!$E216,departments[],3,FALSE) -> Ops | H216: 13 | I216: =VLOOKUP(employees!$H216,locations[#All],3,FALSE) -> Cairo | J216: =_xlfn.XLOOKUP(Table6[[#This Row],[City]],locations[city],locations[Continent]) -> Africa | K216: Mid | L216: Bachelor | M216: 43276 | N216: Hybrid | O216: 2.56 | P216: 8.5 | Q216: 37780.96 | R216: 250 | S216: =DATEDIF(employees!$M216, TODAY(), "y") -> 8 | T216: =VLOOKUP(employees!$H216,locations[#All],4,) -> 0.55 | U216: =employees!$Q216/employees!$T216 -> 68692.655
A217: 216 | B217: Anthony Everett | C217: Female | D217: 63 | E217: 26 | F217: =VLOOKUP(Table6[[#This Row],[department_id]],departments[#All],2,FALSE) -> Procurement | G217: =VLOOKUP(employees!$E217,departments[],3,FALSE) -> Ops | H217: 10 | I217: =VLOOKUP(employees!$H217,locations[#All],3,FALSE) -> Warsaw | J217: =_xlfn.XLOOKUP(Table6[[#This Row],[City]],locations[city],locations[Continent]) -> Europe | K217: Lead | L217: Bachelor | M217: 42206 | N217: Hybrid | O217: 3.06 | P217: 8.2 | Q217: 164973.69 | R217: 341 | S217: =DATEDIF(employees!$M217, TODAY(), "y") -> 11 | T217: =VLOOKUP(employees!$H217,locations[#All],4,) -> 0.95 | U217: =employees!$Q217/employees!$T217 -> 173656.52
A218: 217 | B218: Rodney Morales | C218: Non-binary | D218: 45 | E218: 3 | F218: =VLOOKUP(Table6[[#This Row],[department_id]],departments[#All],2,FALSE) -> Data Engineering | G218: =VLOOKUP(employees!$E218,departments[],3,FALSE) -> Tech | H218: 15 | I218: =VLOOKUP(employees!$H218,locations[#All],3,FALSE) -> Cape Town | J218: =_xlfn.XLOOKUP(Table6[[#This Row],[City]],locations[city],locations[Continent]) -> Africa | K218: Vp | L218: Bachelor | M218: 45565 | N218: Remote | O218: 4.5 | P218: 7 | Q218: 218362.89 | R218: Unknown | S218: =DATEDIF(employees!$M218, TODAY(), "y") -> 1 | T218: =VLOOKUP(employees!$H218,locations[#All],4,) -> 0.7 | U218: =employees!$Q218/employees!$T218 -> 311946.99
A219: 218 | B219: Mark Brown | C219: Male | D219: 35 | E219: 23 | F219: =VLOOKUP(Table6[[#This Row],[department_id]],departments[#All],2,FALSE) -> Legal | G219: =VLOOKUP(employees!$E219,departments[],3,FALSE) -> G&A | H219: 18 | I219: =VLOOKUP(employees!$H219,locations[#All],3,FALSE) -> Buenos Aires | J219: =_xlfn.XLOOKUP(Table6[[#This Row],[City]],locations[city],locations[Continent]) -> South America | K219: Senior | L219: Bachelor | M219: 42336 | N219: Hybrid | O219: 3.99 | P219: 5.2 | Q219: 167853.26 | R219: 604 | S219: =DATEDIF(employees!$M219, TODAY(), "y") -> 10 | T219: =VLOOKUP(employees!$H219,locations[#All],4,) -> 0.65 | U219: =employees!$Q219/employees!$T219 -> 258235.78
A220: 219 | B220: Justin Torres | C220: Male | D220: 20 | E220: 13 | F220: =VLOOKUP(Table6[[#This Row],[department_id]],departments[#All],2,FALSE) -> Sales | G220: =VLOOKUP(employees!$E220,departments[],3,FALSE) -> GTM | H220: 11 | I220: =VLOOKUP(employees!$H220,locations[#All],3,FALSE) -> Bengaluru | J220: =_xlfn.XLOOKUP(Table6[[#This Row],[City]],locations[city],locations[Continent]) -> Asia | K220: Director | L220: High School | M220: 45166 | N220: On-site | O220: 4.22 | P220: 7.7 | Q220: 108891.79 | R220: 3435 | S220: =DATEDIF(employees!$M220, TODAY(), "y") -> 3 | T220: =VLOOKUP(employees!$H220,locations[#All],4,) -> 0.7 | U220: =employees!$Q220/employees!$T220 -> 155559.7
A221: 220 | B221: Bailey Duran Dds | C221: Male | D221: 42 | E221: 12 | F221: =VLOOKUP(Table6[[#This Row],[department_id]],departments[#All],2,FALSE) -> UX Research | G221: =VLOOKUP(employees!$E221,departments[],3,FALSE) -> Product | H221: 13 | I221: =VLOOKUP(employees!$H221,locations[#All],3,FALSE) -> Cairo | J221: =_xlfn.XLOOKUP(Table6[[#This Row],[City]],locations[city],locations[Continent]) -> Africa | K221: Mid | L221: PhD | M221: 45739 | N221: Hybrid | O221: 3.18 | P221: 9.4 | Q221: 46810.98 | R221: 846 | S221: =DATEDIF(employees!$M221, TODAY(), "y") -> 1 | T221: =VLOOKUP(employees!$H221,locations[#All],4,) -> 0.55 | U221: =employees!$Q221/employees!$T221 -> 85110.873
A222: 221 | B222: Courtney Mills | C222: Female | D222: 33 | E222: 24 | F222: =VLOOKUP(Table6[[#This Row],[department_id]],departments[#All],2,FALSE) -> Administration | G222: =VLOOKUP(employees!$E222,departments[],3,FALSE) -> G&A | H222: 5 | I222: =VLOOKUP(employees!$H222,locations[#All],3,FALSE) -> London | J222: =_xlfn.XLOOKUP(Table6[[#This Row],[City]],locations[city],locations[Continent]) -> Europe | K222: Mid | L222: Bachelor | M222: 44450 | N222: On-site | O222: 2.72 | P222: 8.5 | Q222: 50204.86 | R222: 1188 | S222: =DATEDIF(employees!$M222, TODAY(), "y") -> 5 | T222: =VLOOKUP(employees!$H222,locations[#All],4,) -> 1.25 | U222: =employees!$Q222/employees!$T222 -> 40163.888
A223: 222 | B223: Jeremy Dalton | C223: Non-binary | D223: 26 | E223: 2 | F223: =VLOOKUP(Table6[[#This Row],[department_id]],departments[#All],2,FALSE) -> Data Science | G223: =VLOOKUP(employees!$E223,departments[],3,FALSE) -> Tech | H223: 4 | I223: =VLOOKUP(employees!$H223,locations[#All],3,FALSE) -> Toronto | J223: =_xlfn.XLOOKUP(Table6[[#This Row],[City]],locations[city],locations[Continent]) -> North America | K223: Intern | L223: Master | M223: 44450 | N223: On-site | O223: 4.76 | P223: 6.2 | Q223: 43716.66 | R223: 734 | S223: =DATEDIF(employees!$M223, TODAY(), "y") -> 5 | T223: =VLOOKUP(employees!$H223,locations[#All],4,) -> 1.1 | U223: =employees!$Q223/employees!$T223 -> 39742.418
A224: 223 | B224: Elizabeth Oliver Dds | C224: Female | D224: 60 | E224: 18 | F224: =VLOOKUP(Table6[[#This Row],[department_id]],departments[#All],2,FALSE) -> Customer Support | G224: =VLOOKUP(employees!$E224,departments[],3,FALSE) -> GTM | H224: 14 | I224: =VLOOKUP(employees!$H224,locations[#All],3,FALSE) -> Dubai | J224: =_xlfn.XLOOKUP(Table6[[#This Row],[City]],locations[city],locations[Continent]) -> Asia | K224: Director | L224: Bachelor | M224: 43539 | N224: Hybrid | O224: 3.49 | P224: 5.1 | Q224: 117307.65 | R224: 1735 | S224: =DATEDIF(employees!$M224, TODAY(), "y") -> 7 | T224: =VLOOKUP(employees!$H224,locations[#All],4,) -> 1.05 | U224: =employees!$Q224/employees!$T224 -> 111721.57
A225: 224 | B225: Theresa Clark | C225: Male | D225: 37 | E225: 19 | F225: =VLOOKUP(Table6[[#This Row],[department_id]],departments[#All],2,FALSE) -> Human Resources | G225: =VLOOKUP(employees!$E225,departments[],3,FALSE) -> G&A | H225: 14 | I225: =VLOOKUP(employees!$H225,locations[#All],3,FALSE) -> Dubai | J225: =_xlfn.XLOOKUP(Table6[[#This Row],[City]],locations[city],locations[Continent]) -> Asia | K225: Mid | L225: Master | M225: 43399 | N225: Remote | O225: 2.64 | P225: 5.5 | Q225: 85972.82 | R225: 2704 | S225: =DATEDIF(employees!$M225, TODAY(), "y") -> 7 | T225: =VLOOKUP(employees!$H225,locations[#All],4,) -> 1.05 | U225: =employees!$Q225/employees!$T225 -> 81878.876
A226: 225 | B226: Matthew Moore | C226: Non-binary | D226: 51 | E226: 11 | F226: =VLOOKUP(Table6[[#This Row],[department_id]],departments[#All],2,FALSE) -> Design | G226: =VLOOKUP(employees!$E226,departments[],3,FALSE) -> Product | H226: 7 | I226: =VLOOKUP(employees!$H226,locations[#All],3,FALSE) -> Paris | J226: =_xlfn.XLOOKUP(Table6[[#This Row],[City]],locations[city],locations[Continent]) -> Europe | K226: Mid | L226: Bachelor | M226: 43789 | N226: Hybrid | O226: 3.87 | P226: 7.9 | Q226: 105525.06 | R226: 1549 | S226: =DATEDIF(employees!$M226, TODAY(), "y") -> 6 | T226: =VLOOKUP(employees!$H226,locations[#All],4,) -> 1.18 | U226: =employees!$Q226/employees!$T226 -> 89428.017
A227: 226 | B227: Benjamin Smith | C227: Non-binary | D227: 57 | E227: 15 | F227: =VLOOKUP(Table6[[#This Row],[department_id]],departments[#All],2,FALSE) -> Marketing | G227: =VLOOKUP(employees!$E227,departments[],3,FALSE) -> GTM | H227: 20 | I227: =VLOOKUP(employees!$H227,locations[#All],3,FALSE) -> Singapore | J227: =_xlfn.XLOOKUP(Table6[[#This Row],[City]],locations[city],locations[Continent]) -> Asia | K227: Junior | L227: High School | M227: 44076 | N227: On-site | O227: 2.77 | P227: 6.5 | Q227: 64143.35 | R227: 1753 | S227: =DATEDIF(employees!$M227, TODAY(), "y") -> 6 | T227: =VLOOKUP(employees!$H227,locations[#All],4,) -> 1.22 | U227: =employees!$Q227/employees!$T227 -> 52576.516
A228: 227 | B228: Kirk Carter | C228: Non-binary | D228: 44 | E228: 17 | F228: =VLOOKUP(Table6[[#This Row],[department_id]],departments[#All],2,FALSE) -> Customer Success | G228: =VLOOKUP(employees!$E228,departments[],3,FALSE) -> GTM | H228: 13 | I228: =VLOOKUP(employees!$H228,locations[#All],3,FALSE) -> Cairo | J228: =_xlfn.XLOOKUP(Table6[[#This Row],[City]],locations[city],locations[Continent]) -> Africa | K228: Mid | L228: Bachelor | M228: 42769 | N228: Hybrid | O228: 3.74 | P228: 9.4 | Q228: 43929.51 | R228: 3457 | S228: =DATEDIF(employees!$M228, TODAY(), "y") -> 9 | T228: =VLOOKUP(employees!$H228,locations[#All],4,) -> 0.55 | U228: =employees!$Q228/employees!$T228 -> 79871.836
A229: 228 | B229: Michael Warner | C229: Female | D229: 48 | E229: 6 | F229: =VLOOKUP(Table6[[#This Row],[department_id]],departments[#All],2,FALSE) -> Security | G229: =VLOOKUP(employees!$E229,departments[],3,FALSE) -> Tech | H229: 16 | I229: =VLOOKUP(employees!$H229,locations[#All],3,FALSE) -> São Paulo | J229: =_xlfn.XLOOKUP(Table6[[#This Row],[City]],locations[city],locations[Continent]) -> South America | K229: Mid | L229: Bachelor | M229: 43172 | N229: Remote | O229: 4.69 | P229: 7.3 | Q229: 79821.8 | R229: 3149 | S229: =DATEDIF(employees!$M229, TODAY(), "y") -> 8 | T229: =VLOOKUP(employees!$H229,locations[#All],4,) -> 0.8 | U229: =employees!$Q229/employees!$T229 -> 99777.25
A230: 229 | B230: Michael Bradshaw | C230: Non-binary | D230: 51 | E230: 18 | F230: =VLOOKUP(Table6[[#This Row],[department_id]],departments[#All],2,FALSE) -> Customer Support | G230: =VLOOKUP(employees!$E230,departments[],3,FALSE) -> GTM | H230: 17 | I230: =VLOOKUP(employees!$H230,locations[#All],3,FALSE) -> Mexico City | J230: =_xlfn.XLOOKUP(Table6[[#This Row],[City]],locations[city],locations[Continent]) -> South America | K230: Senior | L230: Bachelor | M230: 44991 | N230: Remote | O230: 3.62 | P230: 5.4 | Q230: 41959.64 | R230: 1396 | S230: =DATEDIF(employees!$M230, TODAY(), "y") -> 3 | T230: =VLOOKUP(employees!$H230,locations[#All],4,) -> 0.78 | U230: =employees!$Q230/employees!$T230 -> 53794.41
... A311: 310 | B311: Dawn Summers | C311: Male | D311: 59 | E311: 19 | F311: =VLOOKUP(Table6[[#This Row],[department_id]],departments[#All],2,FALSE) -> Human Resources | G311: =VLOOKUP(employees!$E311,departments[],3,FALSE) -> G&A | H311: 6 | I311: =VLOOKUP(employees!$H311,locations[#All],3,FALSE) -> Berlin | J311: =_xlfn.XLOOKUP(Table6[[#This Row],[City]],locations[city],locations[Continent]) -> Europe | K311: Mid | L311: Bachelor | M311: 42361 | N311: Hybrid | O311: 3.49 | P311: 7.3 | Q311: 56003.49 | R311: 2852 | S311: =DATEDIF(employees!$M311, TODAY(), "y") -> 10 | T311: =VLOOKUP(employees!$H311,locations[#All],4,) -> 1.1 | U311: =employees!$Q311/employees!$T311 -> 50912.264
A312: 311 | B312: Dr. Paul Morgan | C312: Non-binary | D312: 32 | E312: 24 | F312: =VLOOKUP(Table6[[#This Row],[department_id]],departments[#All],2,FALSE) -> Administration | G312: =VLOOKUP(employees!$E312,departments[],3,FALSE) -> G&A | H312: 12 | I312: =VLOOKUP(employees!$H312,locations[#All],3,FALSE) -> Hyderabad | J312: =_xlfn.XLOOKUP(Table6[[#This Row],[City]],locations[city],locations[Continent]) -> Asia | K312: Director | L312: High School | M312: 44279 | N312: On-site | O312: 4.19 | P312: 6.1 | Q312: 86753.05 | R312: Unknown | S312: =DATEDIF(employees!$M312, TODAY(), "y") -> 5 | T312: =VLOOKUP(employees!$H312,locations[#All],4,) -> 0.68 | U312: =employees!$Q312/employees!$T312 -> 127578.01
A313: 312 | B313: Victor Taylor | C313: Male | D313: 24 | E313: 4 | F313: =VLOOKUP(Table6[[#This Row],[department_id]],departments[#All],2,FALSE) -> ML Engineering | G313: =VLOOKUP(employees!$E313,departments[],3,FALSE) -> Tech | H313: 13 | I313: =VLOOKUP(employees!$H313,locations[#All],3,FALSE) -> Cairo | J313: =_xlfn.XLOOKUP(Table6[[#This Row],[City]],locations[city],locations[Continent]) -> Africa | K313: Mid | L313: Master | M313: 44147 | N313: On-site | O313: 3.17 | P313: 8.5 | Q313: 71865.29 | R313: 2207 | S313: =DATEDIF(employees!$M313, TODAY(), "y") -> 5 | T313: =VLOOKUP(employees!$H313,locations[#All],4,) -> 0.55 | U313: =employees!$Q313/employees!$T313 -> 130664.16
A314: 313 | B314: Shannon Ramsey | C314: Female | D314: 32 | E314: 22 | F314: =VLOOKUP(Table6[[#This Row],[department_id]],departments[#All],2,FALSE) -> Accounting | G314: =VLOOKUP(employees!$E314,departments[],3,FALSE) -> G&A | H314: 5 | I314: =VLOOKUP(employees!$H314,locations[#All],3,FALSE) -> London | J314: =_xlfn.XLOOKUP(Table6[[#This Row],[City]],locations[city],locations[Continent]) -> Europe | K314: Mid | L314: Bachelor | M314: 45655 | N314: Remote | O314: 4.37 | P314: 5.1 | Q314: 89687.36 | R314: 2794 | S314: =DATEDIF(employees!$M314, TODAY(), "y") -> 1 | T314: =VLOOKUP(employees!$H314,locations[#All],4,) -> 1.25 | U314: =employees!$Q314/employees!$T314 -> 71749.888
A315: 314 | B315: Tracy Ballard | C315: Male | D315: 43 | E315: 7 | F315: =VLOOKUP(Table6[[#This Row],[department_id]],departments[#All],2,FALSE) -> IT & Helpdesk | G315: =VLOOKUP(employees!$E315,departments[],3,FALSE) -> Tech | H315: 1 | I315: =VLOOKUP(employees!$H315,locations[#All],3,FALSE) -> San Francisco | J315: =_xlfn.XLOOKUP(Table6[[#This Row],[City]],locations[city],locations[Continent]) -> North America | K315: Senior | L315: Master | M315: 43024 | N315: Hybrid | O315: 3.36 | P315: 8.1 | Q315: 145045.29 | R315: 2092 | S315: =DATEDIF(employees!$M315, TODAY(), "y") -> 8 | T315: =VLOOKUP(employees!$H315,locations[#All],4,) -> 1.35 | U315: =employees!$Q315/employees!$T315 -> 107440.96
A316: 315 | B316: Richard Smith | C316: Male | D316: 64 | E316: 20 | F316: =VLOOKUP(Table6[[#This Row],[department_id]],departments[#All],2,FALSE) -> Recruiting | G316: =VLOOKUP(employees!$E316,departments[],3,FALSE) -> G&A | H316: 2 | I316: =VLOOKUP(employees!$H316,locations[#All],3,FALSE) -> New York | J316: =_xlfn.XLOOKUP(Table6[[#This Row],[City]],locations[city],locations[Continent]) -> North America | K316: Senior | L316: High School | M316: 41801 | N316: Hybrid | O316: 2.78 | P316: 6.2 | Q316: 131746.51 | R316: 1826 | S316: =DATEDIF(employees!$M316, TODAY(), "y") -> 12 | T316: =VLOOKUP(employees!$H316,locations[#All],4,) -> 1.3 | U316: =employees!$Q316/employees!$T316 -> 101343.47
A317: 316 | B317: Jordan Chambers | C317: Non-binary | D317: 26 | E317: 22 | F317: =VLOOKUP(Table6[[#This Row],[department_id]],departments[#All],2,FALSE) -> Accounting | G317: =VLOOKUP(employees!$E317,departments[],3,FALSE) -> G&A | H317: 21 | I317: =VLOOKUP(employees!$H317,locations[#All],3,FALSE) -> Sydney | J317: =_xlfn.XLOOKUP(Table6[[#This Row],[City]],locations[city],locations[Continent]) -> Oceania | K317: Intern | L317: Bachelor | M317: 45087 | N317: On-site | O317: 3.89 | P317: 5.7 | Q317: 38072.7 | R317: 1915 | S317: =DATEDIF(employees!$M317, TODAY(), "y") -> 3 | T317: =VLOOKUP(employees!$H317,locations[#All],4,) -> 1.15 | U317: =employees!$Q317/employees!$T317 -> 33106.696
A318: 317 | B318: Lauren Carson | C318: Male | D318: 51 | E318: 24 | F318: =VLOOKUP(Table6[[#This Row],[department_id]],departments[#All],2,FALSE) -> Administration | G318: =VLOOKUP(employees!$E318,departments[],3,FALSE) -> G&A | H318: 20 | I318: =VLOOKUP(employees!$H318,locations[#All],3,FALSE) -> Singapore | J318: =_xlfn.XLOOKUP(Table6[[#This Row],[City]],locations[city],locations[Continent]) -> Asia | K318: Junior | L318: Bachelor | M318: 42573 | N318: On-site | O318: 3.1 | P318: 7.5 | Q318: 40617.44 | R318: 2356 | S318: =DATEDIF(employees!$M318, TODAY(), "y") -> 10 | T318: =VLOOKUP(employees!$H318,locations[#All],4,) -> 1.22 | U318: =employees!$Q318/employees!$T318 -> 33292.984
A319: 318 | B319: Ashley Hall | C319: Male | D319: 64 | E319: 10 | F319: =VLOOKUP(Table6[[#This Row],[department_id]],departments[#All],2,FALSE) -> Product Operations | G319: =VLOOKUP(employees!$E319,departments[],3,FALSE) -> Product | H319: 6 | I319: =VLOOKUP(employees!$H319,locations[#All],3,FALSE) -> Berlin | J319: =_xlfn.XLOOKUP(Table6[[#This Row],[City]],locations[city],locations[Continent]) -> Europe | K319: Junior | L319: Master | M319: 45706 | N319: On-site | O319: 2.51 | P319: 8.2 | Q319: 103240.79 | R319: 2265 | S319: =DATEDIF(employees!$M319, TODAY(), "y") -> 1 | T319: =VLOOKUP(employees!$H319,locations[#All],4,) -> 1.1 | U319: =employees!$Q319/employees!$T319 -> 93855.264
A320: 319 | B320: Stephen Hoffman | C320: Non-binary | D320: 24 | E320: 22 | F320: =VLOOKUP(Table6[[#This Row],[department_id]],departments[#All],2,FALSE) -> Accounting | G320: =VLOOKUP(employees!$E320,departments[],3,FALSE) -> G&A | H320: 16 | I320: =VLOOKUP(employees!$H320,locations[#All],3,FALSE) -> São Paulo | J320: =_xlfn.XLOOKUP(Table6[[#This Row],[City]],locations[city],locations[Continent]) -> South America | K320: Junior | L320: Master | M320: 42377 | N320: On-site | O320: 3.09 | P320: 6.1 | Q320: 52068.25 | R320: 1939 | S320: =DATEDIF(employees!$M320, TODAY(), "y") -> 10 | T320: =VLOOKUP(employees!$H320,locations[#All],4,) -> 0.8 | U320: =employees!$Q320/employees!$T320 -> 65085.312
A321: 320 | B321: Connie Brown | C321: Male | D321: 38 | E321: 15 | F321: =VLOOKUP(Table6[[#This Row],[department_id]],departments[#All],2,FALSE) -> Marketing | G321: =VLOOKUP(employees!$E321,departments[],3,FALSE) -> GTM | H321: 2 | I321: =VLOOKUP(employees!$H321,locations[#All],3,FALSE) -> New York | J321: =_xlfn.XLOOKUP(Table6[[#This Row],[City]],locations[city],locations[Continent]) -> North America | K321: Junior | L321: Bachelor | M321: 43071 | N321: Hybrid | O321: 3.48 | P321: 5.6 | Q321: 114771.25 | R321: 1270 | S321: =DATEDIF(employees!$M321, TODAY(), "y") -> 8 | T321: =VLOOKUP(employees!$H321,locations[#All],4,) -> 1.3 | U321: =employees!$Q321/employees!$T321 -> 88285.577
A322: 321 | B322: Susan Turner | C322: Female | D322: 42 | E322: 1 | F322: =VLOOKUP(Table6[[#This Row],[department_id]],departments[#All],2,FALSE) -> Engineering | G322: =VLOOKUP(employees!$E322,departments[],3,FALSE) -> Tech | H322: 5 | I322: =VLOOKUP(employees!$H322,locations[#All],3,FALSE) -> London | J322: =_xlfn.XLOOKUP(Table6[[#This Row],[City]],locations[city],locations[Continent]) -> Europe | K322: Senior | L322: Master | M322: 43036 | N322: Remote | O322: 3.12 | P322: 8.5 | Q322: 172714.41 | R322: 1015 | S322: =DATEDIF(employees!$M322, TODAY(), "y") -> 8 | T322: =VLOOKUP(employees!$H322,locations[#All],4,) -> 1.25 | U322: =employees!$Q322/employees!$T322 -> 138171.53
A323: 322 | B323: Charles Shah | C323: Female | D323: 44 | E323: 4 | F323: =VLOOKUP(Table6[[#This Row],[department_id]],departments[#All],2,FALSE) -> ML Engineering | G323: =VLOOKUP(employees!$E323,departments[],3,FALSE) -> Tech | H323: 13 | I323: =VLOOKUP(employees!$H323,locations[#All],3,FALSE) -> Cairo | J323: =_xlfn.XLOOKUP(Table6[[#This Row],[City]],locations[city],locations[Continent]) -> Africa | K323: Mid | L323: Master | M323: 45379 | N323: Hybrid | O323: 3.47 | P323: 9.3 | Q323: 50437.84 | R323: 3360 | S323: =DATEDIF(employees!$M323, TODAY(), "y") -> 2 | T323: =VLOOKUP(employees!$H323,locations[#All],4,) -> 0.55 | U323: =employees!$Q323/employees!$T323 -> 91705.164
A324: 323 | B324: Johnathan Davis | C324: Male | D324: 46 | E324: 24 | F324: =VLOOKUP(Table6[[#This Row],[department_id]],departments[#All],2,FALSE) -> Administration | G324: =VLOOKUP(employees!$E324,departments[],3,FALSE) -> G&A | H324: 2 | I324: =VLOOKUP(employees!$H324,locations[#All],3,FALSE) -> New York | J324: =_xlfn.XLOOKUP(Table6[[#This Row],[City]],locations[city],locations[Continent]) -> North America | K324: Director | L324: Master | M324: 42945 | N324: Hybrid | O324: 3.81 | P324: 7.1 | Q324: 173440.54 | R324: Unknown | S324: =DATEDIF(employees!$M324, TODAY(), "y") -> 9 | T324: =VLOOKUP(employees!$H324,locations[#All],4,) -> 1.3 | U324: =employees!$Q324/employees!$T324 -> 133415.8
A325: 324 | B325: Brandy Chavez | C325: Female | D325: 51 | E325: 20 | F325: =VLOOKUP(Table6[[#This Row],[department_id]],departments[#All],2,FALSE) -> Recruiting | G325: =VLOOKUP(employees!$E325,departments[],3,FALSE) -> G&A | H325: 1 | I325: =VLOOKUP(employees!$H325,locations[#All],3,FALSE) -> San Francisco | J325: =_xlfn.XLOOKUP(Table6[[#This Row],[City]],locations[city],locations[Continent]) -> North America | K325: Lead | L325: High School | M325: 42710 | N325: Hybrid | O325: 2.61 | P325: 6.3 | Q325: 158350.57 | R325: 3076 | S325: =DATEDIF(employees!$M325, TODAY(), "y") -> 9 | T325: =VLOOKUP(employees!$H325,locations[#All],4,) -> 1.35 | U325: =employees!$Q325/employees!$T325 -> 117296.72
A326: 325 | B326: Natalie Bautista | C326: Non-binary | D326: 41 | E326: 22 | F326: =VLOOKUP(Table6[[#This Row],[department_id]],departments[#All],2,FALSE) -> Accounting | G326: =VLOOKUP(employees!$E326,departments[],3,FALSE) -> G&A | H326: 17 | I326: =VLOOKUP(employees!$H326,locations[#All],3,FALSE) -> Mexico City | J326: =_xlfn.XLOOKUP(Table6[[#This Row],[City]],locations[city],locations[Continent]) -> South America | K326: Lead | L326: Bachelor | M326: 43474 | N326: Hybrid | O326: 3.92 | P326: 7.1 | Q326: 105664.73 | R326: 554 | S326: =DATEDIF(employees!$M326, TODAY(), "y") -> 7 | T326: =VLOOKUP(employees!$H326,locations[#All],4,) -> 0.78 | U326: =employees!$Q326/employees!$T326 -> 135467.6
A327: 326 | B327: Patrick Moore | C327: Male | D327: 61 | E327: 22 | F327: =VLOOKUP(Table6[[#This Row],[department_id]],departments[#All],2,FALSE) -> Accounting | G327: =VLOOKUP(employees!$E327,departments[],3,FALSE) -> G&A | H327: 21 | I327: =VLOOKUP(employees!$H327,locations[#All],3,FALSE) -> Sydney | J327: =_xlfn.XLOOKUP(Table6[[#This Row],[City]],locations[city],locations[Continent]) -> Oceania | K327: Mid | L327: Master | M327: 42087 | N327: Hybrid | O327: 3.58 | P327: 7.4 | Q327: 72703.4 | R327: 2388 | S327: =DATEDIF(employees!$M327, TODAY(), "y") -> 11 | T327: =VLOOKUP(employees!$H327,locations[#All],4,) -> 1.15 | U327: =employees!$Q327/employees!$T327 -> 63220.348
A328: 327 | B328: Brett Burns | C328: Male | D328: 52 | E328: 11 | F328: =VLOOKUP(Table6[[#This Row],[department_id]],departments[#All],2,FALSE) -> Design | G328: =VLOOKUP(employees!$E328,departments[],3,FALSE) -> Product | H328: 8 | I328: =VLOOKUP(employees!$H328,locations[#All],3,FALSE) -> Barcelona | J328: =_xlfn.XLOOKUP(Table6[[#This Row],[City]],locations[city],locations[Continent]) -> Europe | K328: Mid | L328: Bachelor | M328: 43918 | N328: Hybrid | O328: 3.43 | P328: 6.1 | Q328: 103000.09 | R328: 1156 | S328: =DATEDIF(employees!$M328, TODAY(), "y") -> 6 | T328: =VLOOKUP(employees!$H328,locations[#All],4,) -> 1.05 | U328: =employees!$Q328/employees!$T328 -> 98095.324
A329: 328 | B329: Trevor Johnson | C329: Female | D329: 27 | E329: 15 | F329: =VLOOKUP(Table6[[#This Row],[department_id]],departments[#All],2,FALSE) -> Marketing | G329: =VLOOKUP(employees!$E329,departments[],3,FALSE) -> GTM | H329: 3 | I329: =VLOOKUP(employees!$H329,locations[#All],3,FALSE) -> Austin | J329: =_xlfn.XLOOKUP(Table6[[#This Row],[City]],locations[city],locations[Continent]) -> North America | K329: Lead | L329: PhD | M329: 45302 | N329: Hybrid | O329: 2.54 | P329: 6.9 | Q329: 100640.29 | R329: 538 | S329: =DATEDIF(employees!$M329, TODAY(), "y") -> 2 | T329: =VLOOKUP(employees!$H329,locations[#All],4,) -> 1.05 | U329: =employees!$Q329/employees!$T329 -> 95847.895
A330: 329 | B330: Jeremy Sampson | C330: Non-binary | D330: 55 | E330: 27 | F330: =VLOOKUP(Table6[[#This Row],[department_id]],departments[#All],2,FALSE) -> Facilities | G330: =VLOOKUP(employees!$E330,departments[],3,FALSE) -> Ops | H330: 3 | I330: =VLOOKUP(employees!$H330,locations[#All],3,FALSE) -> Austin | J330: =_xlfn.XLOOKUP(Table6[[#This Row],[City]],locations[city],locations[Continent]) -> North America | K330: Lead | L330: Bachelor | M330: 44135 | N330: Hybrid | O330: 4.69 | P330: 6.7 | Q330: 64963.69 | R330: 2992 | S330: =DATEDIF(employees!$M330, TODAY(), "y") -> 5 | T330: =VLOOKUP(employees!$H330,locations[#All],4,) -> 1.05 | U330: =employees!$Q330/employees!$T330 -> 61870.181
A331: 330 | B331: Ariana Jennings | C331: Non-binary | D331: 62 | E331: 15 | F331: =VLOOKUP(Table6[[#This Row],[department_id]],departments[#All],2,FALSE) -> Marketing | G331: =VLOOKUP(employees!$E331,departments[],3,FALSE) -> GTM | H331: 11 | I331: =VLOOKUP(employees!$H331,locations[#All],3,FALSE) -> Bengaluru | J331: =_xlfn.XLOOKUP(Table6[[#This Row],[City]],locations[city],locations[Continent]) -> Asia | K331: Senior | L331: Bachelor | M331: 45515 | N331: Hybrid | O331: 2.72 | P331: 8.2 | Q331: 49070.91 | R331: 845 | S331: =DATEDIF(employees!$M331, TODAY(), "y") -> 2 | T331: =VLOOKUP(employees!$H331,locations[#All],4,) -> 0.7 | U331: =employees!$Q331/employees!$T331 -> 70101.3
A332: 331 | B332: Vanessa Howard | C332: Non-binary | D332: 26 | E332: 21 | F332: =VLOOKUP(Table6[[#This Row],[department_id]],departments[#All],2,FALSE) -> Finance | G332: =VLOOKUP(employees!$E332,departments[],3,FALSE) -> G&A | H332: 10 | I332: =VLOOKUP(employees!$H332,locations[#All],3,FALSE) -> Warsaw | J332: =_xlfn.XLOOKUP(Table6[[#This Row],[City]],locations[city],locations[Continent]) -> Europe | K332: Senior | L332: High School | M332: 44702 | N332: On-site | O332: 2.82 | P332: 8.4 | Q332: 115546.59 | R332: 1073 | S332: =DATEDIF(employees!$M332, TODAY(), "y") -> 4 | T332: =VLOOKUP(employees!$H332,locations[#All],4,) -> 0.95 | U332: =employees!$Q332/employees!$T332 -> 121627.99
A333: 332 | B333: Colton Martinez | C333: Male | D333: 49 | E333: 20 | F333: =VLOOKUP(Table6[[#This Row],[department_id]],departments[#All],2,FALSE) -> Recruiting | G333: =VLOOKUP(employees!$E333,departments[],3,FALSE) -> G&A | H333: 7 | I333: =VLOOKUP(employees!$H333,locations[#All],3,FALSE) -> Paris | J333: =_xlfn.XLOOKUP(Table6[[#This Row],[City]],locations[city],locations[Continent]) -> Europe | K333: Junior | L333: Master | M333: 44858 | N333: On-site | O333: 3.28 | P333: 8.6 | Q333: 48775.66 | R333: 1074 | S333: =DATEDIF(employees!$M333, TODAY(), "y") -> 3 | T333: =VLOOKUP(employees!$H333,locations[#All],4,) -> 1.18 | U333: =employees!$Q333/employees!$T333 -> 41335.305
A334: 333 | B334: Jordan Bates | C334: Female | D334: 62 | E334: 22 | F334: =VLOOKUP(Table6[[#This Row],[department_id]],departments[#All],2,FALSE) -> Accounting | G334: =VLOOKUP(employees!$E334,departments[],3,FALSE) -> G&A | H334: 19 | I334: =VLOOKUP(employees!$H334,locations[#All],3,FALSE) -> Tokyo | J334: =_xlfn.XLOOKUP(Table6[[#This Row],[City]],locations[city],locations[Continent]) -> Asia | K334: Junior | L334: Bachelor | M334: 45330 | N334: Hybrid | O334: 4.72 | P334: 5 | Q334: 76409.55 | R334: 1461 | S334: =DATEDIF(employees!$M334, TODAY(), "y") -> 2 | T334: =VLOOKUP(employees!$H334,locations[#All],4,) -> 1.2 | U334: =employees!$Q334/employees!$T334 -> 63674.625
A335: 334 | B335: Linda Smith | C335: Male | D335: 64 | E335: 14 | F335: =VLOOKUP(Table6[[#This Row],[department_id]],departments[#All],2,FALSE) -> Sales Operations | G335: =VLOOKUP(employees!$E335,departments[],3,FALSE) -> GTM | H335: 19 | I335: =VLOOKUP(employees!$H335,locations[#All],3,FALSE) -> Tokyo | J335: =_xlfn.XLOOKUP(Table6[[#This Row],[City]],locations[city],locations[Continent]) -> Asia | K335: Mid | L335: Bachelor | M335: 45804 | N335: Hybrid | O335: 2.8 | P335: 6.9 | Q335: 117651.77 | R335: 1342 | S335: =DATEDIF(employees!$M335, TODAY(), "y") -> 1 | T335: =VLOOKUP(employees!$H335,locations[#All],4,) -> 1.2 | U335: =employees!$Q335/employees!$T335 -> 98043.142
A336: 335 | B336: Dana Martinez | C336: Female | D336: 45 | E336: 17 | F336: =VLOOKUP(Table6[[#This Row],[department_id]],departments[#All],2,FALSE) -> Customer Success | G336: =VLOOKUP(employees!$E336,departments[],3,FALSE) -> GTM | H336: 13 | I336: =VLOOKUP(employees!$H336,locations[#All],3,FALSE) -> Cairo | J336: =_xlfn.XLOOKUP(Table6[[#This Row],[City]],locations[city],locations[Continent]) -> Africa | K336: Mid | L336: PhD | M336: 43673 | N336: Remote | O336: 3.54 | P336: 5.6 | Q336: 40732.9 | R336: 2393 | S336: =DATEDIF(employees!$M336, TODAY(), "y") -> 7 | T336: =VLOOKUP(employees!$H336,locations[#All],4,) -> 0.55 | U336: =employees!$Q336/employees!$T336 -> 74059.818
... A346: 345 | B346: Kayla Rodriguez | C346: Male | D346: 42 | E346: 26 | F346: =VLOOKUP(Table6[[#This Row],[department_id]],departments[#All],2,FALSE) -> Procurement | G346: =VLOOKUP(employees!$E346,departments[],3,FALSE) -> Ops | H346: 17 | I346: =VLOOKUP(employees!$H346,locations[#All],3,FALSE) -> Mexico City | J346: =_xlfn.XLOOKUP(Table6[[#This Row],[City]],locations[city],locations[Continent]) -> South America | K346: Junior | L346: Bachelor | M346: 44944 | N346: On-site | O346: 3.26 | P346: 6.7 | Q346: 43165.47 | R346: 598 | S346: =DATEDIF(employees!$M346, TODAY(), "y") -> 3 | T346: =VLOOKUP(employees!$H346,locations[#All],4,) -> 0.78 | U346: =employees!$Q346/employees!$T346 -> 55340.346
...

Sheet departments
A1: department_id | B1: department | C1: category
A2: 1 | B2: Engineering | C2: Tech
A3: 2 | B3: Data Science | C3: Tech
A4: 3 | B4: Data Engineering | C4: Tech
A5: 4 | B5: ML Engineering | C5: Tech
A6: 5 | B6: Platform | C6: Tech
A7: 6 | B7: Security | C7: Tech
A8: 7 | B8: IT & Helpdesk | C8: Tech
A9: 8 | B9: QA & Testing | C9: Tech
A10: 9 | B10: Product Management | C10: Product
A11: 10 | B11: Product Operations | C11: Product
A12: 11 | B12: Design | C12: Product
A13: 12 | B13: UX Research | C13: Product
... A28: 27 | B28: Facilities | C28: Ops

Sheet locations
A1: location_id | B1: country | C1: city | D1: cost_index | E1: Continent
A2: 1 | B2: United States | C2: San Francisco | D2: 1.35 | E2: North America
A3: 2 | B3: United States | C3: New York | D3: 1.3 | E3: North America
A4: 3 | B4: United States | C4: Austin | D4: 1.05 | E4: North America
A5: 4 | B5: Canada | C5: Toronto | D5: 1.1 | E5: North America
A6: 5 | B6: United Kingdom | C6: London | D6: 1.25 | E6: Europe
A7: 6 | B7: Germany | C7: Berlin | D7: 1.1 | E7: Europe
A8: 7 | B8: France | C8: Paris | D8: 1.18 | E8: Europe
A9: 8 | B9: Spain | C9: Barcelona | D9: 1.05 | E9: Europe
A10: 9 | B10: Netherlands | C10: Amsterdam | D10: 1.15 | E10: Europe
A11: 10 | B11: Poland | C11: Warsaw | D11: 0.95 | E11: Europe
A12: 11 | B12: India | C12: Bengaluru | D12: 0.7 | E12: Asia
A13: 12 | B13: India | C13: Hyderabad | D13: 0.68 | E13: Asia
... A22: 21 | B22: Australia | C22: Sydney | D22: 1.15 | E22: Oceania

Sheet org_edges
A1: source_manager_id | B1: target_employee_id
A2: 2177 | B2: 1
A3: 2225 | B3: 2
A4: 43 | B4: 3
A5: 290 | B5: 4
A6: 1603 | B6: 5
A7: 2865 | B7: 6
A8: 778 | B8: 7
A9: 1834 | B9: 8
A10: 2497 | B10: 9
A11: 346 | B11: 10
A12: 2411 | B12: 11
A13: 873 | B13: 12
... A3435: 2623 | B3435: 3500

Sheet promotions
A1: employee_id | B1: promotion_date | C1: from_level | D1: to_level
A2: 2 | B2: 44702 | C2: Mid | D2: Senior
A3: 3 | B3: 45802 | C3: Senior | D3: Lead
A4: 6 | B4: 43782 | C4: Junior | D4: Mid
A5: 6 | B5: 43903 | C5: Mid | D5: Senior
A6: 6 | B6: 45237 | C6: Senior | D6: Lead
A7: 6 | B7: 45366 | C7: Lead | D7: Manager
A8: 7 | B8: 43609 | C8: Mid | D8: Senior
A9: 7 | B9: 44775 | C9: Senior | D9: Lead
A10: 8 | B10: 44065 | C10: Mid | D10: Senior
A11: 9 | B11: 44320 | C11: Mid | D11: Senior
A12: 15 | B12: 44271 | C12: Junior | D12: Mid
A13: 15 | B13: 45061 | C13: Mid | D13: Senior
... A2703: 3497 | B2703: 45863 | C2703: Mid | D2703: Senior

Sheet salaries_annual
A1: employee_id | B1: year | C1: seniority_level | D1: salary_usd | E1: Annual Salary Growth %
A2: 1 | B2: 2020 | C2: Intern | D2: 39578 | E2: =IF(A3=A2,(D3-D2)/D2,1) -> 0.026782556
A3: 1 | B3: 2021 | C3: Intern | D3: 40638 | E3: =IF(A4=A3,(D4-D3)/D3,1) -> 0.043161573
A4: 1 | B4: 2022 | C4: Intern | D4: 42392 | E4: =IF(A5=A4,(D5-D4)/D4,1) -> 0.052840159
A5: 1 | B5: 2023 | C5: Intern | D5: 44632 | E5: =IF(A6=A5,(D6-D5)/D5,1) -> 0.043511382
A6: 1 | B6: 2024 | C6: Intern | D6: 46574 | E6: =IF(A7=A6,(D7-D6)/D6,1) -> 0.065766307
A7: 1 | B7: 2025 | C7: Intern | D7: 49637 | E7: =IF(A8=A7,(D8-D7)/D7,1) -> 1
A8: 2 | B8: 2014 | C8: Mid | D8: 141489 | E8: =IF(A9=A8,(D9-D8)/D8,1) -> 0.02435525
A9: 2 | B9: 2015 | C9: Mid | D9: 144935 | E9: =IF(A10=A9,(D10-D9)/D9,1) -> 0.029475282
A10: 2 | B10: 2016 | C10: Mid | D10: 149207 | E10: =IF(A11=A10,(D11-D10)/D10,1) -> 0.031814861
A11: 2 | B11: 2017 | C11: Mid | D11: 153954 | E11: =IF(A12=A11,(D12-D11)/D11,1) -> 0.024124089
A12: 2 | B12: 2018 | C12: Mid | D12: 157668 | E12: =IF(A13=A12,(D13-D12)/D12,1) -> 0.032612832
A13: 2 | B13: 2019 | C13: Mid | D13: 162810 | E13: =IF(A14=A13,(D14-D13)/D13,1) -> 0.029199681
... A22853: 3500 | B22853: 2025 | C22853: Mid | D22853: 123501 | E22853: =IF(A22854=A22853,(D22854-D22853)/D22853,1) -> 1

Sheet Pivot Tables
A1: Employee Count by Department Category
A2: department_category | B2: Total
A3: G&A | B3: 805
A4: GTM | B4: 795
A5: Ops | B5: 389
A6: Product | B6: 487
A7: Tech | B7: 1024
A8: Grand Total | B8: 3500
A16: Average Salary by Department
A17: department_category | B17: department_name | C17: Total
A18: G&A | B18: Accounting | C18: 12518336
B19: Administration | C19: 8168376.2
B20: Finance | C20: 16962474
B21: Human Resources | C21: 11950230
B22: Legal | C22: 22717858
B23: Recruiting | C23: 11423612
A24: G&A Total | C24: 83740885
A25: GTM | B25: Content Marketing | C25: 9157875.9
B26: Customer Success | C26: 10301433
B27: Customer Support | C27: 7095206.2
B28: Marketing | C28: 15311086
B29: Sales | C29: 12409856
B30: Sales Operations | C30: 13927324
A31: GTM Total | C31: 68202781
A32: Ops | B32: Facilities | C32: 8712400.7
B33: Operations | C33: 13173264
B34: Procurement | C34: 13686251
A35: Ops Total | C35: 35571916
A36: Product | B36: Design | C36: 12968197
B37: Product Management | C37: 17230181
B38: Product Operations | C38: 13675869
B39: UX Research | C39: 16237613
A40: Product Total | C40: 60111860
A41: Tech | B41: Data Engineering | C41: 20506812
B42: Data Science | C42: 17683254
B43: Engineering | C43: 19781047
B44: IT & Helpdesk | C44: 10921895
B45: ML Engineering | C45: 19233314
B46: Platform | C46: 22436198
B47: QA & Testing | C47: 12874105
B48: Security | C48: 17982490
A49: Tech Total | C49: 1.4141912e+08
A50: Grand Total | C50: 3.8904656e+08
A52: Employee Count by Location
A53: Continent | B53: Total
A54: Africa | B54: 351
A55: Asia | B55: 838
A56: Europe | B56: 999
A57: North America | B57: 698
A58: Oceania | B58: 163
A59: South America | B59: 451
A60: Grand Total | B60: 3500
A70: Gender Distribution
A71: gender | B71: Total
A72: Female | B72: 1172
A73: Male | B73: 1149
A74: Non-binary | B74: 1179
A75: Grand Total | B75: 3500
A85: Experience Level vs Salary Average
A86: seniority | B86: Total
A87: Director | B87: 200439.58
A88: Intern | B88: 38813.293
A89: Junior | B89: 68289.764
A90: Lead | B90: 149062.72
A91: Manager | B91: 165396.98
A92: Mid | B92: 89728.142
A93: Senior | B93: 121369.27
A94: Vp | B94: 294944.87
A95: Grand Total | B95: 111156.16
